{"name":"p_10222018_1726","fleet_size":"FINITE","coord_mode":"REAL","username":["planner1"],"date_format":"YYYY-MM-DDTHH:mmZ","vehicles":[{"id":"VEHICLEA","type_id":" TAXI","driver_name":"DRIVER","start_address":{"id":"Start_VEHICLEA","postal":"138647","lat":1.29976,"lon":103.787458},"end_address":{"id":"138647","postal":"138647","lat":1.29976,"lon":103.787458},"return_to_depot":false,"earliest_start":"2018-10-22T08:00+08:00","latest_end":"2018-10-22T20:00+08:00","num_assigned":0,"max_num_job":1000}],"vehicle_types":[{"id":" TAXI","name":" TAXI","capacity":[1000],"fixed_costs":100,"distance_dependent_costs":0.00010000000000000002,"time_dependent_costs":0.0017000000000000001,"waiting_time_dependent_costs":0.0017000000000000001}],"services":[{"id":"A1","name":null,"type":"delivery","size":[60],"address":{"id":"109705","postal":"109705","name":"MAGGIE","address":"6 TEMASEK BOULEVARD SUNTEC TOWER FOUR 32-03","lat":1.28221769648725,"lon":103.803662042557},"service_duration":720,"time_windows":[{"start":"2018-10-22T15:00+08:00","end":"2018-10-22T17:00+08:00"}],"allowed_vehicles":null,"assigned_to":null,"priority":2,"status":1,"usergroup":null,"dueTime":"2018-10-22T17:00+08:00","deliveryDue":"2018-10-22T17:00+08:00"},{"id":"A2","name":null,"type":"delivery","size":[40],"address":{"id":"109705","postal":"109705","name":"Choo","address":"7 TEMASEK BOULEVARD SUNTEC TOWER ONE 40-01a","lat":1.28221769648725,"lon":103.803662042557},"service_duration":720,"time_windows":[{"start":"2018-10-22T15:00+08:00","end":"2018-10-22T17:00+08:00"}],"allowed_vehicles":null,"assigned_to":null,"priority":2,"status":1,"usergroup":null,"dueTime":"2018-10-22T17:00+08:00","deliveryDue":"2018-10-22T17:00+08:00"},{"id":"A3","name":null,"type":"delivery","size":[620],"address":{"id":"109705","postal":"109705","name":"Cheryl","address":"6 RAFFLES QUAY - 13-00","lat":1.28221769648725,"lon":103.803662042557},"service_duration":720,"time_windows":[{"start":"2018-10-22T15:00+08:00","end":"2018-10-22T17:00+08:00"}],"allowed_vehicles":null,"assigned_to":null,"priority":2,"status":1,"usergroup":null,"dueTime":"2018-10-22T17:00+08:00","deliveryDue":"2018-10-22T17:00+08:00"},{"id":"A4","name":null,"type":"delivery","size":[510],"address":{"id":"109705","postal":"109705","name":"Cheryl","address":"6 RAFFLES QUAY - 17-00","lat":1.28221769648725,"lon":103.803662042557},"service_duration":720,"time_windows":[{"start":"2018-10-22T15:00+08:00","end":"2018-10-22T17:00+08:00"}],"allowed_vehicles":null,"assigned_to":null,"priority":2,"status":1,"usergroup":null,"dueTime":"2018-10-22T17:00+08:00","deliveryDue":"2018-10-22T17:00+08:00"},{"id":"A5","name":null,"type":"delivery","size":[970],"address":{"id":"109705","postal":"109705","name":"Cheryl","address":"6 RAFFLES QUAY - 23-00","lat":1.28221769648725,"lon":103.803662042557},"service_duration":720,"time_windows":[{"start":"2018-10-22T15:00+08:00","end":"2018-10-22T17:00+08:00"}],"allowed_vehicles":null,"assigned_to":null,"priority":2,"status":1,"usergroup":null,"dueTime":"2018-10-22T17:00+08:00","deliveryDue":"2018-10-22T17:00+08:00"}],"shipments":[],"solutions":[],"addresses":[{"id":"Start_VEHICLEA","postal":"138647","lat":1.29976,"lon":103.787458},{"id":"138647","postal":"138647","lat":1.29976,"lon":103.787458},{"id":"109705","postal":"109705","name":"MAGGIE","address":"6 TEMASEK BOULEVARD SUNTEC TOWER FOUR 32-03","lat":1.28221769648725,"lon":103.803662042557}],"items":[{"id":"Weight","weight":1,"description":"in Kg"}],"_id":"p_planner_2018-10-22","created_date":"2018-10-22T10:26:14.800Z","modified_date":"2018-10-22T10:26:14.800Z"}